{"SURVIVAL":{"bedSpawnLocation":{"==":"org.bukkit.Location","world":"survival","x":192.5,"y":64.1,"z":35.5,"pitch":0.0,"yaw":0.0},"offHandItem":{"==":"org.bukkit.inventory.ItemStack","v":2584,"type":"SHIELD","meta":{"==":"ItemMeta","meta-type":"TILE_ENTITY","Damage":77,"blockMaterial":"SHIELD"}},"inventoryContents":{"10":{"==":"org.bukkit.inventory.ItemStack","v":2584,"type":"BREAD","amount":10},"11":{"==":"org.bukkit.inventory.ItemStack","v":2584,"type":"COBBLESTONE","amount":29},"12":{"==":"org.bukkit.inventory.ItemStack","v":2584,"type":"ARROW","amount":32},"13":{"==":"org.bukkit.inventory.ItemStack","v":2584,"type":"IRON_SHOVEL","meta":{"==":"ItemMeta","meta-type":"UNSPECIFIC","Damage":57}},"14":{"==":"org.bukkit.inventory.ItemStack","v":2584,"type":"SPRUCE_LOG","amount":5},"36":{"==":"org.bukkit.inventory.ItemStack","v":2584,"type":"IRON_BOOTS","meta":{"==":"ItemMeta","meta-type":"UNSPECIFIC","Damage":20}},"15":{"==":"org.bukkit.inventory.ItemStack","v":2584,"type":"BUCKET"},"37":{"==":"org.bukkit.inventory.ItemStack","v":2584,"type":"IRON_LEGGINGS","meta":{"==":"ItemMeta","meta-type":"UNSPECIFIC","Damage":20}},"16":{"==":"org.bukkit.inventory.ItemStack","v":2584,"type":"FISHING_ROD","meta":{"==":"ItemMeta","meta-type":"UNSPECIFIC","enchants":{"LUCK":3,"LURE":3,"MENDING":1,"DURABILITY":3},"repair-cost":1,"Damage":53}},"38":{"==":"org.bukkit.inventory.ItemStack","v":2584,"type":"DIAMOND_CHESTPLATE","meta":{"==":"ItemMeta","meta-type":"UNSPECIFIC","enchants":{"PROTECTION_ENVIRONMENTAL":4,"DURABILITY":3},"repair-cost":3,"Damage":12}},"17":{"==":"org.bukkit.inventory.ItemStack","v":2584,"type":"COOKED_COD","amount":45},"39":{"==":"org.bukkit.inventory.ItemStack","v":2584,"type":"IRON_HELMET","meta":{"==":"ItemMeta","meta-type":"UNSPECIFIC","Damage":20}},"18":{"==":"org.bukkit.inventory.ItemStack","v":2584,"type":"BONE"},"19":{"==":"org.bukkit.inventory.ItemStack","v":2584,"type":"WHEAT_SEEDS","amount":22},"0":{"==":"org.bukkit.inventory.ItemStack","v":2584,"type":"DIAMOND_SWORD","meta":{"==":"ItemMeta","meta-type":"UNSPECIFIC","enchants":{"DAMAGE_ALL":4},"repair-cost":1,"Damage":32}},"1":{"==":"org.bukkit.inventory.ItemStack","v":2584,"type":"DIAMOND_PICKAXE","meta":{"==":"ItemMeta","meta-type":"UNSPECIFIC","enchants":{"DIG_SPEED":4},"repair-cost":7,"Damage":80}},"2":{"==":"org.bukkit.inventory.ItemStack","v":2584,"type":"BOW","meta":{"==":"ItemMeta","meta-type":"UNSPECIFIC","enchants":{"ARROW_FIRE":1,"MENDING":1,"ARROW_DAMAGE":5,"DURABILITY":3},"repair-cost":7}},"3":{"==":"org.bukkit.inventory.ItemStack","v":2584,"type":"FLINT_AND_STEEL","meta":{"==":"ItemMeta","meta-type":"UNSPECIFIC","Damage":3}},"4":{"==":"org.bukkit.inventory.ItemStack","v":2584,"type":"TORCH","amount":16},"5":{"==":"org.bukkit.inventory.ItemStack","v":2584,"type":"STONE_AXE","meta":{"==":"ItemMeta","meta-type":"UNSPECIFIC","Damage":72}},"6":{"==":"org.bukkit.inventory.ItemStack","v":2584,"type":"COOKED_SALMON","amount":43},"9":{"==":"org.bukkit.inventory.ItemStack","v":2584,"type":"GUNPOWDER"},"40":{"==":"org.bukkit.inventory.ItemStack","v":2584,"type":"SHIELD","meta":{"==":"ItemMeta","meta-type":"TILE_ENTITY","Damage":77,"blockMaterial":"SHIELD"}},"20":{"==":"org.bukkit.inventory.ItemStack","v":2584,"type":"WHEAT","amount":13}},"enderChestContents":{},"armorContents":{"0":{"==":"org.bukkit.inventory.ItemStack","v":2584,"type":"IRON_BOOTS","meta":{"==":"ItemMeta","meta-type":"UNSPECIFIC","Damage":20}},"1":{"==":"org.bukkit.inventory.ItemStack","v":2584,"type":"IRON_LEGGINGS","meta":{"==":"ItemMeta","meta-type":"UNSPECIFIC","Damage":20}},"2":{"==":"org.bukkit.inventory.ItemStack","v":2584,"type":"DIAMOND_CHESTPLATE","meta":{"==":"ItemMeta","meta-type":"UNSPECIFIC","enchants":{"PROTECTION_ENVIRONMENTAL":4,"DURABILITY":3},"repair-cost":3,"Damage":12}},"3":{"==":"org.bukkit.inventory.ItemStack","v":2584,"type":"IRON_HELMET","meta":{"==":"ItemMeta","meta-type":"UNSPECIFIC","Damage":20}}},"potions":[],"stats":{"ex":"2.9548218","ma":"300","fl":"20","el":"8","hp":"20.0","xp":"0.07038949","txp":"3160","fd":"0.0","ft":"-20","sa":"2.2000008","ra":"300"}}}